cadcutils/__init__.py
cadcutils/exceptions.py
cadcutils/old_get_cert.py
cadcutils/version.py
cadcutils/net/__init__.py
cadcutils/net/auth.py
cadcutils/net/group.py
cadcutils/net/groups_client.py
cadcutils/net/netutils.py
cadcutils/net/ws.py
cadcutils/net/wscapabilities.py
cadcutils/net/group_xml/__init__.py
cadcutils/net/group_xml/group_property_reader.py
cadcutils/net/group_xml/group_property_writer.py
cadcutils/net/group_xml/group_reader.py
cadcutils/net/group_xml/group_writer.py
cadcutils/net/group_xml/groups_reader.py
cadcutils/net/group_xml/groups_writer.py
cadcutils/net/group_xml/user_reader.py
cadcutils/net/group_xml/user_writer.py
cadcutils/net/group_xml/tests/__init__.py
cadcutils/net/group_xml/tests/test_group_property_reader_writer.py
cadcutils/net/group_xml/tests/test_group_reader_writer.py
cadcutils/net/group_xml/tests/test_groups_reader_writer.py
cadcutils/net/group_xml/tests/test_user_reader_writer.py
cadcutils/net/tests/__init__.py
cadcutils/net/tests/test_auth.py
cadcutils/net/tests/test_group.py
cadcutils/net/tests/test_groups_client.py
cadcutils/net/tests/test_int_groups.py
cadcutils/net/tests/test_netutils.py
cadcutils/net/tests/test_ws.py
cadcutils/net/tests/test_wscapabilities.py
cadcutils/util/__init__.py
cadcutils/util/config.py
cadcutils/util/utils.py
cadcutils-1.5.5.dist-info/licenses/LICENSE
cadcutils-1.5.5.dist-info/METADATA
cadcutils-1.5.5.dist-info/WHEEL
cadcutils-1.5.5.dist-info/entry_points.txt
cadcutils-1.5.5.dist-info/top_level.txt
cadcutils-1.5.5.dist-info/RECORD
