Metadata-Version: 2.4
Name: cadcutils
Version: 1.5.5
Summary: Generic CADC Python libary of utilities
Home-page: http://www.cadc-ccda.hia-iha.nrc-cnrc.gc.ca
Author: Canadian Astronomy Data Centre
Author-email: cadc@nrc-cnrc.gc.ca
License: AGPLv3
Classifier: Natural Language :: English
Classifier: License :: OSI Approved :: GNU Affero General Public License v3
Classifier: Programming Language :: Python
Classifier: Programming Language :: Python :: 3
Requires-Python: >=3.9, <4
License-File: LICENSE
Requires-Dist: setuptools>=36.0
Requires-Dist: requests>=2.8
Requires-Dist: lxml>=3.7.0
Requires-Dist: html2text
Requires-Dist: distro
Requires-Dist: pyopenssl
Requires-Dist: packaging
Provides-Extra: test
Requires-Dist: pytest; extra == "test"
Requires-Dist: pytest-cov>=2.5.1; extra == "test"
Requires-Dist: flake8>=3.4.1; extra == "test"
Requires-Dist: funcsigs==1.0.2; extra == "test"
Requires-Dist: mock>=2.0.0; extra == "test"
Requires-Dist: xml-compare>=1.0.5; extra == "test"
Dynamic: author
Dynamic: author-email
Dynamic: classifier
Dynamic: description
Dynamic: home-page
Dynamic: license
Dynamic: license-file
Dynamic: requires-python
Dynamic: summary
